FlaskDiscordAuth/discord_auth.py
flaskdiscordauth-0.2.0.dist-info/METADATA
flaskdiscordauth-0.2.0.dist-info/WHEEL
flaskdiscordauth-0.2.0.dist-info/licenses/LICENSE
flaskdiscordauth-0.2.0.dist-info/RECORD
