Metadata-Version: 2.4
Name: FlaskDiscordAuth
Version: 0.2.0
Summary: A Python library to simplify Discord OAuth2 authentication with Flask applications
Project-URL: Homepage, https://github.com/fakelag28/flask-discord-auth
Project-URL: Source, https://github.com/fakelag28/flask-discord-auth
Author-email: fakelag28 <fakelag712@gmail.com>
License-Expression: MIT
License-File: LICENSE
Keywords: authentication,discord,flask,oauth2
Classifier: License :: OSI Approved :: MIT License
Classifier: Operating System :: OS Independent
Classifier: Programming Language :: Python :: 3
Requires-Python: >=3.6
Requires-Dist: flask>=1.0
Requires-Dist: requests>=2.0
